CHANGES.txt
MANIFEST.in
README.rst
setup.py
macauthlib/__init__.py
macauthlib/noncecache.py
macauthlib/utils.py
macauthlib.egg-info/PKG-INFO
macauthlib.egg-info/SOURCES.txt
macauthlib.egg-info/dependency_links.txt
macauthlib.egg-info/not-zip-safe
macauthlib.egg-info/requires.txt
macauthlib.egg-info/top_level.txt
macauthlib/tests/__init__.py
macauthlib/tests/test_noncecache.py
macauthlib/tests/test_request_objects.py
macauthlib/tests/test_signatures.py
macauthlib/tests/test_utils.py