Metadata-Version: 1.0
Name: macauthlib
Version: 0.6.0
Summary: macauth
Home-page: https://github.com/mozilla-services/macauthlib
Author: Mozilla Services
Author-email: services-dev@mozilla.org
License: MPLv2.0
Keywords: authentication MAC Access HTTP request signing
Platform: UNKNOWN
Classifier: Programming Language :: Python
Classifier: License :: OSI Approved :: Mozilla Public License 2.0 (MPL 2.0)
